[
    {
        "age": null,
        "album": "",
        "author": "Matt Wales",
        "bookmarked": false,
        "comments": [],
        "date_created": "2025-12-03T17:34:09.794086+00:00",
        "date_dead_since": null,
        "date_published": "2025-12-03T17:06:49+00:00",
        "description": "<img src=\"https://assetsio.gnwcdn.com/Image-showing-Aloy-from-the-Horizon-series-on-the-left-and-a-female-character-from-Light-of-Motiram-on-the-right.jpg?width=690&quality=85&format=jpg&auto=webp\" /> <p>\n<a href=\"https://www.eurogamer.net/companies/tencent\">Tencent</a> has agreed to halt all promotion and public testing of Light of Motiram - the post-apocalyptic open-world survival game Sony previously accused of being a \"slavish clone\" of PlayStation's Horizon series in a lawsuit - as the two companies battle it out in court.\n</p> <p><a href=\"https://www.eurogamer.net/tencents-alleged-horizon-rip-off-is-ironically-back-in-the-news-as-company-agrees-to-halt-promotion-amid-sony-lawsuit\">Read more</a></p>",
        "id": 4229191,
        "language": "en-gb",
        "link": "https://www.eurogamer.net/tencents-alleged-horizon-rip-off-is-ironically-back-in-the-news-as-company-agrees-to-halt-promotion-amid-sony-lawsuit",
        "manual_status_code": 0,
        "page_rating": 27,
        "page_rating_contents": 86,
        "page_rating_visits": 0,
        "page_rating_votes": 0,
        "permanent": false,
        "source__id": 107,
        "source_url": "https://www.eurogamer.net/feed",
        "status_code": 0,
        "tags": [],
        "thumbnail": "https://assetsio.gnwcdn.com/Image-showing-Aloy-from-the-Horizon-series-on-the-left-and-a-female-character-from-Light-of-Motiram-on-the-right.jpg?width=690&quality=85&format=jpg&auto=webp",
        "title": "Tencent's alleged Horizon rip-off is ironically back in the news as company agrees to halt promotion amid Sony lawsuit",
        "vote": 0
    },
    {
        "age": null,
        "album": "",
        "author": "Connor Makar",
        "bookmarked": false,
        "comments": [],
        "date_created": "2025-12-03T17:34:10.076270+00:00",
        "date_dead_since": null,
        "date_published": "2025-12-03T17:03:56+00:00",
        "description": "<img src=\"https://assetsio.gnwcdn.com/Battlefield-6-Official-Multiplayer-Gameplay-Trailer-1-27-screenshot.png?width=690&quality=85&format=jpg&auto=webp\" /> <p><a href=\"https://www.eurogamer.net/games/battlefield-2025\">Battlefield 6</a> has received both netcode and hit registration improvements ahead of the Winter Offensive update, which is set to go live on the 9th December.</p> <p><a href=\"https://www.eurogamer.net/battlefield-6-addresses-primary-community-complaint-improves-hit-registrations-and-netcode-ahead-of-winter-offensive-update\">Read more</a></p>",
        "id": 4229192,
        "language": "en-gb",
        "link": "https://www.eurogamer.net/battlefield-6-addresses-primary-community-complaint-improves-hit-registrations-and-netcode-ahead-of-winter-offensive-update",
        "manual_status_code": 0,
        "page_rating": 27,
        "page_rating_contents": 86,
        "page_rating_visits": 0,
        "page_rating_votes": 0,
        "permanent": false,
        "source__id": 107,
        "source_url": "https://www.eurogamer.net/feed",
        "status_code": 0,
        "tags": [],
        "thumbnail": "https://assetsio.gnwcdn.com/Battlefield-6-Official-Multiplayer-Gameplay-Trailer-1-27-screenshot.png?width=690&quality=85&format=jpg&auto=webp",
        "title": "Battlefield 6 addresses primary community complaint, improves hit registrations and netcode ahead of Winter Offensive update",
        "vote": 0
    },
    {
        "age": null,
        "album": "",
        "author": "Victoria Phillips Kennedy",
        "bookmarked": false,
        "comments": [],
        "date_created": "2025-12-03T16:25:39.937358+00:00",
        "date_dead_since": null,
        "date_published": "2025-12-03T16:10:57+00:00",
        "description": "<img src=\"https://assetsio.gnwcdn.com/Lara-Croft-in-Shadow-of-the-Tomb-Raider-wearing-a-decorated-skeletal-mask-and-her-hood-up.jpg?width=690&quality=85&format=jpg&auto=webp\" /> <p>Amazon's upcoming live-action <a href=\"https://www.eurogamer.net/tomb-raider-games-order\">Tomb Raider series</a> from Pheobe Waller-Bridge will interconnect with the video games, rather than being a standalone story with its own continuity in the vein of the Angelina Jolie films.</p> <p><a href=\"https://www.eurogamer.net/amazons-live-action-tomb-raider-adaptation-will-reinvent-the-franchise-and-interconnect-with-the-games\">Read more</a></p>",
        "id": 4228452,
        "language": "en-gb",
        "link": "https://www.eurogamer.net/amazons-live-action-tomb-raider-adaptation-will-reinvent-the-franchise-and-interconnect-with-the-games",
        "manual_status_code": 0,
        "page_rating": 27,
        "page_rating_contents": 86,
        "page_rating_visits": 0,
        "page_rating_votes": 0,
        "permanent": false,
        "source__id": 107,
        "source_url": "https://www.eurogamer.net/feed",
        "status_code": 0,
        "tags": [],
        "thumbnail": "https://assetsio.gnwcdn.com/Lara-Croft-in-Shadow-of-the-Tomb-Raider-wearing-a-decorated-skeletal-mask-and-her-hood-up.jpg?width=690&quality=85&format=jpg&auto=webp",
        "title": "Amazon's live-action Tomb Raider adaptation will \"reinvent the franchise\" and interconnect with the games",
        "vote": 0
    },
    {
        "age": null,
        "album": "",
        "author": "Connor Makar",
        "bookmarked": false,
        "comments": [],
        "date_created": "2025-12-03T16:25:40.048581+00:00",
        "date_dead_since": null,
        "date_published": "2025-12-03T15:58:13+00:00",
        "description": "<img src=\"https://assetsio.gnwcdn.com/Marathon-_-Save-the-Date-Trailer-1-4-screenshot-(2)-(1).png?width=690&quality=85&format=jpg&auto=webp\" /> <p>Antireal, the artist at the heart of a plagiarism scandal involving Bungie's upcoming extraction shooter Marathon, has posted a statement on social media indicating the saga has come to a close.</p> <p><a href=\"https://www.eurogamer.net/marathon-plagiarism-scandal-resolved-satisfaction-of-artist\">Read more</a></p>",
        "id": 4228453,
        "language": "en-gb",
        "link": "https://www.eurogamer.net/marathon-plagiarism-scandal-resolved-satisfaction-of-artist",
        "manual_status_code": 0,
        "page_rating": 27,
        "page_rating_contents": 86,
        "page_rating_visits": 0,
        "page_rating_votes": 0,
        "permanent": false,
        "source__id": 107,
        "source_url": "https://www.eurogamer.net/feed",
        "status_code": 0,
        "tags": [],
        "thumbnail": "https://assetsio.gnwcdn.com/Marathon-_-Save-the-Date-Trailer-1-4-screenshot-(2)-(1).png?width=690&quality=85&format=jpg&auto=webp",
        "title": "Bungie's Marathon plagiarism scandal finally resolved to the \"satisfaction\" of impacted artist",
        "vote": 0
    },
    {
        "age": null,
        "album": "",
        "author": "Matt Wales",
        "bookmarked": false,
        "comments": [],
        "date_created": "2025-12-03T16:25:40.189824+00:00",
        "date_dead_since": null,
        "date_published": "2025-12-03T15:57:35+00:00",
        "description": "<img src=\"https://assetsio.gnwcdn.com/horses-header-epic.jpg?width=690&quality=85&format=jpg&auto=webp\" /> <p>\nSaturnalia developer Santa Ragione's first-person narrative horror Horses has received a last-minute ban from the Epic Games Store. Epic was one of several storefronts confirmed to have approved a build for release when news of Horses' ban from Steam emerged, but it has now reversed its decision, citing what Santa Ragione calls \"broad and demonstrably incorrect claims\".\n</p> <p><a href=\"https://www.eurogamer.net/horses-gets-eleventh-hour-ban-from-epic-games-store\">Read more</a></p>",
        "id": 4228454,
        "language": "en-gb",
        "link": "https://www.eurogamer.net/horses-gets-eleventh-hour-ban-from-epic-games-store",
        "manual_status_code": 0,
        "page_rating": 27,
        "page_rating_contents": 86,
        "page_rating_visits": 0,
        "page_rating_votes": 0,
        "permanent": false,
        "source__id": 107,
        "source_url": "https://www.eurogamer.net/feed",
        "status_code": 0,
        "tags": [],
        "thumbnail": "https://assetsio.gnwcdn.com/horses-header-epic.jpg?width=690&quality=85&format=jpg&auto=webp",
        "title": "Horses gets last-minute ban from Epic Games Store following Steam controversy, despite apparent earlier approval",
        "vote": 0
    },
    {
        "age": null,
        "album": "",
        "author": "Ed Nightingale",
        "bookmarked": false,
        "comments": [],
        "date_created": "2025-12-03T16:25:40.293620+00:00",
        "date_dead_since": null,
        "date_published": "2025-12-03T15:36:22+00:00",
        "description": "<img src=\"https://assetsio.gnwcdn.com/Resident-Evil-Requiem---Reveal-Trailer-2-0-screenshot.png?width=690&quality=85&format=jpg&auto=webp\" /> <p>Fresh footage of Resident Evil Requiem was shown on Japanese television, and it's very reminiscent of classic series gameplay.</p> <p><a href=\"https://www.eurogamer.net/fresh-resident-evil-requiem-footage-return-classic-zombie-form\">Read more</a></p>",
        "id": 4228455,
        "language": "en-gb",
        "link": "https://www.eurogamer.net/fresh-resident-evil-requiem-footage-return-classic-zombie-form",
        "manual_status_code": 0,
        "page_rating": 27,
        "page_rating_contents": 86,
        "page_rating_visits": 0,
        "page_rating_votes": 0,
        "permanent": false,
        "source__id": 107,
        "source_url": "https://www.eurogamer.net/feed",
        "status_code": 0,
        "tags": [],
        "thumbnail": "https://assetsio.gnwcdn.com/Resident-Evil-Requiem---Reveal-Trailer-2-0-screenshot.png?width=690&quality=85&format=jpg&auto=webp",
        "title": "Fresh Resident Evil Requiem footage indicates a return to classic, zombie-infested form",
        "vote": 0
    },
    {
        "age": null,
        "album": "",
        "author": "Ed Nightingale",
        "bookmarked": false,
        "comments": [],
        "date_created": "2025-12-03T15:21:56.966979+00:00",
        "date_dead_since": null,
        "date_published": "2025-12-03T14:42:53+00:00",
        "description": "<img src=\"https://assetsio.gnwcdn.com/Clair-Obscur_-Expedition-33_20250413203735.png?width=690&quality=85&format=jpg&auto=webp\" /> <p><a href=\"https://www.eurogamer.net/games/clair-obscur-expedition-33\">Clair Obscur: Expedition 33</a> is the biggest third-party launch on Xbox Game Pass this year, with game director Guillaume Broche stating the subscription service allowed the studio to reach a wider audience.</p> <p><a href=\"https://www.eurogamer.net/clair-obscur-expedition-33-xbox-game-passs-biggest-third-party-success-2025\">Read more</a></p>",
        "id": 4227838,
        "language": "en-gb",
        "link": "https://www.eurogamer.net/clair-obscur-expedition-33-xbox-game-passs-biggest-third-party-success-2025",
        "manual_status_code": 0,
        "page_rating": 27,
        "page_rating_contents": 86,
        "page_rating_visits": 0,
        "page_rating_votes": 0,
        "permanent": false,
        "source__id": 107,
        "source_url": "https://www.eurogamer.net/feed",
        "status_code": 0,
        "tags": [],
        "thumbnail": "https://assetsio.gnwcdn.com/Clair-Obscur_-Expedition-33_20250413203735.png?width=690&quality=85&format=jpg&auto=webp",
        "title": "Clair Obscur: Expedition 33 is Xbox Game Pass's biggest third-party success in 2025",
        "vote": 0
    },
    {
        "age": null,
        "album": "",
        "author": "Victoria Phillips Kennedy",
        "bookmarked": false,
        "comments": [],
        "date_created": "2025-12-03T14:15:17.225444+00:00",
        "date_dead_since": null,
        "date_published": "2025-12-03T13:29:53+00:00",
        "description": "<img src=\"https://assetsio.gnwcdn.com/Samus-from-the-Metroid-Prime-4-Beyond-keyart-reaching-out-her-hand-with-a-purple-aura-overlaid-on-an-image-of-Blonde-Blazer-in-Dispatch-wearing-a-blue-mask.-Her-eyes-are-glowing-yellow.jpg?width=690&quality=85&format=jpg&auto=webp\" /> <p><a href=\"https://www.eurogamer.net/games/metroid-prime-4\">Metroid Prime 4: Beyond</a> has cast a new voice actress for Samus.</p> <p><a href=\"https://www.eurogamer.net/samus-death-screams-are-no-longer-jennifer-hale-as-dispatch-actress-takes-over-role-for-metroid-prime-4-beyond\">Read more</a></p>",
        "id": 4227258,
        "language": "en-gb",
        "link": "https://www.eurogamer.net/samus-death-screams-are-no-longer-jennifer-hale-as-dispatch-actress-takes-over-role-for-metroid-prime-4-beyond",
        "manual_status_code": 0,
        "page_rating": 27,
        "page_rating_contents": 86,
        "page_rating_visits": 0,
        "page_rating_votes": 0,
        "permanent": false,
        "source__id": 107,
        "source_url": "https://www.eurogamer.net/feed",
        "status_code": 0,
        "tags": [],
        "thumbnail": "https://assetsio.gnwcdn.com/Samus-from-the-Metroid-Prime-4-Beyond-keyart-reaching-out-her-hand-with-a-purple-aura-overlaid-on-an-image-of-Blonde-Blazer-in-Dispatch-wearing-a-blue-mask.-Her-eyes-are-glowing-yellow.jpg?width=690&quality=85&format=jpg&auto=webp",
        "title": "Samus' death screams are no longer Jennifer Hale, as Dispatch actress takes over role for Metroid Prime 4: Beyond",
        "vote": 0
    },
    {
        "age": null,
        "album": "",
        "author": "Ed Nightingale",
        "bookmarked": false,
        "comments": [],
        "date_created": "2025-12-03T13:09:23.653397+00:00",
        "date_dead_since": null,
        "date_published": "2025-12-03T12:40:30+00:00",
        "description": "<img src=\"https://assetsio.gnwcdn.com/CHRONO-TRIGGER-%E2%80%93-Launch-Trailer-0-38-screenshot-(1).png?width=690&quality=85&format=jpg&auto=webp\" /> <p>Dragon Quest creator Yuji Horii has said he \"can't talk about\" future plans for <a href=\"https://www.eurogamer.net/games/chrono-trigger\">Chrono Trigger</a>, suggesting something is indeed in the works.</p> <p><a href=\"https://www.eurogamer.net/dragon-quest-creator-future-chrono-trigger-plans-remake-speculation\">Read more</a></p>",
        "id": 4226707,
        "language": "en-gb",
        "link": "https://www.eurogamer.net/dragon-quest-creator-future-chrono-trigger-plans-remake-speculation",
        "manual_status_code": 0,
        "page_rating": 27,
        "page_rating_contents": 86,
        "page_rating_visits": 0,
        "page_rating_votes": 0,
        "permanent": false,
        "source__id": 107,
        "source_url": "https://www.eurogamer.net/feed",
        "status_code": 0,
        "tags": [],
        "thumbnail": "https://assetsio.gnwcdn.com/CHRONO-TRIGGER-%E2%80%93-Launch-Trailer-0-38-screenshot-(1).png?width=690&quality=85&format=jpg&auto=webp",
        "title": "Dragon Quest creator \"can't talk about\" future Chrono Trigger plans, sparking more remake speculation",
        "vote": 0
    },
    {
        "age": null,
        "album": "",
        "author": "Matt Wales",
        "bookmarked": false,
        "comments": [],
        "date_created": "2025-12-03T13:09:23.886253+00:00",
        "date_dead_since": null,
        "date_published": "2025-12-03T12:26:38+00:00",
        "description": "<img src=\"https://assetsio.gnwcdn.com/no-players-online.jpg?width=690&quality=85&format=jpg&auto=webp\" /> <p>\nWell-received horror game No Players Online has returned to Steam after nearly three weeks of unavailability, which its developer Beeswax Games has blamed on an \"unfounded\" DMCA takedown notice filed by a \"former friend\".\n</p> <p><a href=\"https://www.eurogamer.net/well-received-horror-no-players-online-returns-to-steam-following-unfounded-dmca\">Read more</a></p>",
        "id": 4226708,
        "language": "en-gb",
        "link": "https://www.eurogamer.net/well-received-horror-no-players-online-returns-to-steam-following-unfounded-dmca",
        "manual_status_code": 0,
        "page_rating": 27,
        "page_rating_contents": 86,
        "page_rating_visits": 0,
        "page_rating_votes": 0,
        "permanent": false,
        "source__id": 107,
        "source_url": "https://www.eurogamer.net/feed",
        "status_code": 0,
        "tags": [],
        "thumbnail": "https://assetsio.gnwcdn.com/no-players-online.jpg?width=690&quality=85&format=jpg&auto=webp",
        "title": "\"It's crazy to me that someone can just take down our game\" - well-received horror No Players Online returns to Steam following \"unfounded\" DMCA",
        "vote": 0
    },
    {
        "age": null,
        "album": "",
        "author": "Victoria Phillips Kennedy",
        "bookmarked": false,
        "comments": [],
        "date_created": "2025-12-03T13:09:24.134733+00:00",
        "date_dead_since": null,
        "date_published": "2025-12-03T12:13:11+00:00",
        "description": "<img src=\"https://assetsio.gnwcdn.com/Astarian-from-BG3-and-Ciri-from-The-Witcher-4.jpg?width=690&quality=85&format=jpg&auto=webp\" /> <p>A senior developer who worked on Larian's much loved and critically acclaimed <a href=\"https://www.eurogamer.net/baldurs-gate-3-a-critical-success-with-critical-failures\">Baldur's Gate 3</a> has moved studios, and is now working with Witcher 4 and Cyberpunk studio CD Projekt Red.</p> <p><a href=\"https://www.eurogamer.net/senior-baldurs-gate-3-developer-rolls-dice-and-joins-the-witcher-4-studio-cd-projekt-red\">Read more</a></p>",
        "id": 4226709,
        "language": "en-gb",
        "link": "https://www.eurogamer.net/senior-baldurs-gate-3-developer-rolls-dice-and-joins-the-witcher-4-studio-cd-projekt-red",
        "manual_status_code": 0,
        "page_rating": 27,
        "page_rating_contents": 86,
        "page_rating_visits": 0,
        "page_rating_votes": 0,
        "permanent": false,
        "source__id": 107,
        "source_url": "https://www.eurogamer.net/feed",
        "status_code": 0,
        "tags": [],
        "thumbnail": "https://assetsio.gnwcdn.com/Astarian-from-BG3-and-Ciri-from-The-Witcher-4.jpg?width=690&quality=85&format=jpg&auto=webp",
        "title": "Senior Baldur's Gate 3 developer rolls dice and joins The Witcher 4 studio CD Projekt Red",
        "vote": 0
    },
    {
        "age": null,
        "album": "",
        "author": "Victoria Phillips Kennedy",
        "bookmarked": false,
        "comments": [],
        "date_created": "2025-12-03T12:04:37.058925+00:00",
        "date_dead_since": null,
        "date_published": "2025-12-03T11:19:20+00:00",
        "description": "<img src=\"https://assetsio.gnwcdn.com/A-lot-of-Yoshis-racing-in-Mario-Kart-World.jpg?width=690&quality=85&format=jpg&auto=webp\" /> <p>Nintendo has released a new update for <a href=\"https://www.eurogamer.net/games/mario-kart-world\">Mario Kart World</a>, and it's another big one.</p> <p><a href=\"https://www.eurogamer.net/huge-mario-kart-world-update-changes-course-layouts-dash-food-reappearances-and-so-much-more\">Read more</a></p>",
        "id": 4226278,
        "language": "en-gb",
        "link": "https://www.eurogamer.net/huge-mario-kart-world-update-changes-course-layouts-dash-food-reappearances-and-so-much-more",
        "manual_status_code": 0,
        "page_rating": 27,
        "page_rating_contents": 86,
        "page_rating_visits": 0,
        "page_rating_votes": 0,
        "permanent": false,
        "source__id": 107,
        "source_url": "https://www.eurogamer.net/feed",
        "status_code": 0,
        "tags": [],
        "thumbnail": "https://assetsio.gnwcdn.com/A-lot-of-Yoshis-racing-in-Mario-Kart-World.jpg?width=690&quality=85&format=jpg&auto=webp",
        "title": "Huge Mario Kart World update changes course layouts, Dash food reappearances and so much more",
        "vote": 0
    },
    {
        "age": null,
        "album": "",
        "author": "Robert Purchese",
        "bookmarked": false,
        "comments": [],
        "date_created": "2025-12-03T12:04:37.197038+00:00",
        "date_dead_since": null,
        "date_published": "2025-12-03T11:08:56+00:00",
        "description": "<img src=\"https://assetsio.gnwcdn.com/An-Avowed-NPC-with-large-hairy-ears.jpg?width=690&quality=85&format=jpg&auto=webp\" /> <p>Obsidian Entertainment, one of gaming's busiest developers, has announced a delay for this year's remaining <a href=\"https://www.eurogamer.net/games/avowed\">Avowed</a> update. This was to include a Photo mode and New Game Plus mode, among other things, and it will now be held back - as well as enlarged - for the game's anniversary on 18th February 2026.</p> <p><a href=\"https://www.eurogamer.net/avowed-photo-mode-new-game-plus-update-delayed\">Read more</a></p>",
        "id": 4226279,
        "language": "en-gb",
        "link": "https://www.eurogamer.net/avowed-photo-mode-new-game-plus-update-delayed",
        "manual_status_code": 0,
        "page_rating": 27,
        "page_rating_contents": 86,
        "page_rating_visits": 0,
        "page_rating_votes": 0,
        "permanent": false,
        "source__id": 107,
        "source_url": "https://www.eurogamer.net/feed",
        "status_code": 0,
        "tags": [],
        "thumbnail": "https://assetsio.gnwcdn.com/An-Avowed-NPC-with-large-hairy-ears.jpg?width=690&quality=85&format=jpg&auto=webp",
        "title": "Avowed Photo mode and New Game Plus delayed, as Obsidian makes the update something bigger",
        "vote": 0
    },
    {
        "age": null,
        "album": "",
        "author": "Connor Makar",
        "bookmarked": false,
        "comments": [],
        "date_created": "2025-12-03T11:00:00.390596+00:00",
        "date_dead_since": null,
        "date_published": "2025-12-03T10:06:29+00:00",
        "description": "<img src=\"https://assetsio.gnwcdn.com/mass-effect-legendary-edition-photo-mode-detailed-1618564454815.jpg?width=690&quality=85&format=jpg&auto=webp\" /> <p>According to new filings, Saudi Arabia's Public Investment Fund is set to own the vast majority of EA if the proposed record-breaking acquisition goes through.</p> <p><a href=\"https://www.eurogamer.net/ea-almost-entirely-owned-by-saudi-arabia-sale\">Read more</a></p>",
        "id": 4225813,
        "language": "en-gb",
        "link": "https://www.eurogamer.net/ea-almost-entirely-owned-by-saudi-arabia-sale",
        "manual_status_code": 0,
        "page_rating": 27,
        "page_rating_contents": 86,
        "page_rating_visits": 0,
        "page_rating_votes": 0,
        "permanent": false,
        "source__id": 107,
        "source_url": "https://www.eurogamer.net/feed",
        "status_code": 0,
        "tags": [],
        "thumbnail": "https://assetsio.gnwcdn.com/mass-effect-legendary-edition-photo-mode-detailed-1618564454815.jpg?width=690&quality=85&format=jpg&auto=webp",
        "title": "EA will be almost entirely owned by Saudi Arabia if sale goes through, according to new filing",
        "vote": 0
    },
    {
        "age": null,
        "album": "",
        "author": "Victoria Phillips Kennedy",
        "bookmarked": false,
        "comments": [],
        "date_created": "2025-12-03T09:56:00.555172+00:00",
        "date_dead_since": null,
        "date_published": "2025-12-03T09:51:20+00:00",
        "description": "<img src=\"https://assetsio.gnwcdn.com/Mina-the-Hollower-screenshot-showing-a-pixel-mouse-leaping-through-a-dark-sky-towards-the-camera.jpg?width=690&quality=85&format=jpg&auto=webp\" /> <p><a href=\"https://www.eurogamer.net/games/shovel-knight\">Shovel Knight</a> developer Yacht Club Games is at a \"make-or-break\" moment in the studio's history, and needs Mina the Hollower to do well.</p> <p><a href=\"https://www.eurogamer.net/shovel-knight-developer-at-a-make-or-break-moment-as-all-eyes-focus-on-its-brilliant-upcoming-release-mina-the-hollower\">Read more</a></p>",
        "id": 4225434,
        "language": "en-gb",
        "link": "https://www.eurogamer.net/shovel-knight-developer-at-a-make-or-break-moment-as-all-eyes-focus-on-its-brilliant-upcoming-release-mina-the-hollower",
        "manual_status_code": 0,
        "page_rating": 27,
        "page_rating_contents": 86,
        "page_rating_visits": 0,
        "page_rating_votes": 0,
        "permanent": false,
        "source__id": 107,
        "source_url": "https://www.eurogamer.net/feed",
        "status_code": 0,
        "tags": [],
        "thumbnail": "https://assetsio.gnwcdn.com/Mina-the-Hollower-screenshot-showing-a-pixel-mouse-leaping-through-a-dark-sky-towards-the-camera.jpg?width=690&quality=85&format=jpg&auto=webp",
        "title": "Shovel Knight developer at a \"make-or-break\" moment as all eyes focus on its brilliant upcoming release, Mina the Hollower",
        "vote": 0
    }
]